tinymenu/__init__.py
tinymenu/tinymenu.py
tinymenu-0.1.0.dist-info/DESCRIPTION.rst
tinymenu-0.1.0.dist-info/METADATA
tinymenu-0.1.0.dist-info/RECORD
tinymenu-0.1.0.dist-info/WHEEL
tinymenu-0.1.0.dist-info/metadata.json
tinymenu-0.1.0.dist-info/top_level.txt
