Metadata-Version: 2.0
Name: tinymenu
Version: 0.1.0
Summary: Simplifies creation of command-line menus
Home-page: https://github.com/QiuDev/tinymenu
Author: QiuDev
Author-email: qiudev@protonmail.com
Maintainer: QiuDev
License: MIT
Keywords: menu command commandline cli crossplatform xplatform
Platform: UNKNOWN
Classifier: Development Status :: 5 - Production/Stable
Classifier: Environment :: Console
Classifier: Intended Audience :: Developers
Classifier: License :: OSI Approved :: MIT License
Classifier: Operating System :: OS Independent
Classifier: Programming Language :: Python :: 2
Classifier: Programming Language :: Python :: 2.7
Classifier: Programming Language :: Python :: 3
Classifier: Programming Language :: Python :: 3.4
Classifier: Programming Language :: Python :: 3.5
Classifier: Programming Language :: Python :: 3.6
Classifier: Topic :: Terminals
Requires-Python: >=2.6
